logless/.pylintrc
logless/__init__.py
logless/main.py
logless-0.2.2.dist-info/LICENSE
logless-0.2.2.dist-info/WHEEL
logless-0.2.2.dist-info/METADATA
logless-0.2.2.dist-info/RECORD
